barsup_swagger/__init__.py
barsup_swagger/__pycache__/spec.cpython-34.pyc
barsup_swagger/__pycache__/__init__.cpython-34.pyc
barsup_swagger/static/swagger/index.html
barsup_swagger/static/swagger/swagger-ui.js
barsup_swagger/static/swagger/o2c.html
barsup_swagger/static/swagger/swagger-ui.min.js
barsup_swagger/static/swagger/lib/jquery.ba-bbq.min.js
barsup_swagger/static/swagger/lib/jquery-1.8.0.min.js
barsup_swagger/static/swagger/lib/highlight.7.3.pack.js
barsup_swagger/static/swagger/lib/swagger-oauth.js
barsup_swagger/static/swagger/lib/shred.bundle.js
barsup_swagger/static/swagger/lib/swagger-client.js
barsup_swagger/static/swagger/lib/marked.js
barsup_swagger/static/swagger/lib/underscore-min.js
barsup_swagger/static/swagger/lib/handlebars-2.0.0.js
barsup_swagger/static/swagger/lib/jquery.wiggle.min.js
barsup_swagger/static/swagger/lib/jquery.slideto.min.js
barsup_swagger/static/swagger/lib/backbone-min.js
barsup_swagger/static/swagger/css/reset.css
barsup_swagger/static/swagger/css/typography.css
barsup_swagger/static/swagger/css/screen.css
barsup_swagger/static/swagger/fonts/droid-sans-v6-latin-regular.woff
barsup_swagger/static/swagger/fonts/droid-sans-v6-latin-700.woff
barsup_swagger/static/swagger/fonts/droid-sans-v6-latin-700.eot
barsup_swagger/static/swagger/fonts/droid-sans-v6-latin-regular.woff2
barsup_swagger/static/swagger/fonts/droid-sans-v6-latin-regular.ttf
barsup_swagger/static/swagger/fonts/droid-sans-v6-latin-700.svg
barsup_swagger/static/swagger/fonts/droid-sans-v6-latin-regular.eot
barsup_swagger/static/swagger/fonts/droid-sans-v6-latin-regular.svg
barsup_swagger/static/swagger/fonts/droid-sans-v6-latin-700.ttf
barsup_swagger/static/swagger/fonts/droid-sans-v6-latin-700.woff2
barsup_swagger/static/swagger/images/logo_small.png
barsup_swagger-0.1.0.dist-info/METADATA
barsup_swagger-0.1.0.dist-info/DESCRIPTION.rst
barsup_swagger-0.1.0.dist-info/metadata.json
barsup_swagger-0.1.0.dist-info/WHEEL
barsup_swagger-0.1.0.dist-info/top_level.txt
barsup_swagger-0.1.0.dist-info/RECORD
