Metadata-Version: 2.0
Name: barsup-swagger
Version: 0.1.0
Summary: Swagger.io API UI for barsup-core-based applications
